phytoolkit/__init__.py
phytoolkit/phytoolkit.py
phytoolkit/base/__init__.py
phytoolkit/base/installer.py
phytoolkit/exception/__init__.py
phytoolkit/exception/installationexception.py
phytoolkit/helper/__init__.py
phytoolkit/helper/consolehelper.py
phytoolkit/helper/nethelper.py
phytoolkit/helper/oshelper.py
phytoolkit/qe/__init__.py
phytoolkit/siesta/__init__.py
phytoolkit/siesta/installer.py
phytoolkit/vasp/__init__.py
phytoolkit/vasp/installer.py
phytoolkit-0.2.1a0.dist-info/LICENSE
phytoolkit-0.2.1a0.dist-info/METADATA
phytoolkit-0.2.1a0.dist-info/WHEEL
phytoolkit-0.2.1a0.dist-info/entry_points.txt
phytoolkit-0.2.1a0.dist-info/top_level.txt
phytoolkit-0.2.1a0.dist-info/RECORD
