Metadata-Version: 2.1
Name: phytoolkit
Version: 0.2.1a0
Summary: An installer toolkit for installing a bunch of common simulation tools
Home-page: https://github.com/lalluanthoor/phytools
Author: Lallu Anthoor
Author-email: lalluanthoor@gmail.com
License: MIT
Platform: Linux
Classifier: Development Status :: 3 - Alpha
Classifier: Environment :: Console
Classifier: Intended Audience :: Education
Classifier: Intended Audience :: Science/Research
Classifier: License :: OSI Approved :: MIT License
Classifier: Natural Language :: English
Classifier: Operating System :: POSIX :: Linux
Classifier: Programming Language :: Python :: 3
Classifier: Programming Language :: Python :: 3.5
Classifier: Programming Language :: Python :: 3.6
Classifier: Programming Language :: Python :: 3.7
Classifier: Programming Language :: Python :: 3.8
Classifier: Programming Language :: Python :: 3.9
Classifier: Topic :: Education
Classifier: Topic :: Scientific/Engineering :: Physics
Classifier: Topic :: Scientific/Engineering
Requires-Python: >=3.5
Requires-Dist: click (>=7.1.2)
Requires-Dist: colorama (>=0.4.4)
Requires-Dist: requests (>=2.25.1)
